<?xml version="1.0" encoding="UTF-8"?>
<MF0 version="1.1" packageUris="http://schema.mathworks.com/mf0/ci/19700101 http://schema.mathworks.com/mf0/sl_modelref_info/R2023a http://schema.mathworks.com/mf0/slexec_mm_sto/R2023a_202208151321 http://schema.mathworks.com/mf0/sltp_mm/R2023a_202209151115">
  <ModelRefInfoRepo.ModelRefInfoRoot type="ModelRefInfoRepo.ModelRefInfoRoot" uuid="3f4282c9-af53-4c40-91ef-2b0b1bb6164d">
    <JITEngines>s2FH9IDPL79BYar4RVO7NqB</JITEngines>
    <JITEngines>sV5uQuz76713LF1SxaPIChH</JITEngines>
    <JITEngines>sjLTP0aneMpczrtjBY4AUuC</JITEngines>
    <JITEngines>swdP3zUsEPkb1ch3tOTn6wD</JITEngines>
    <JITEngines>sziaPEYZ5Jpuie2ZBRQRnqG</JITEngines>
    <calibrationData type="ModelRefInfoRepo.CalibrationData" uuid="667b7f53-a528-4fe4-8377-619397ec3b1f">
      <ModelName>sim_ROV_v0_R2018b</ModelName>
    </calibrationData>
    <childModelRefInfo type="ModelRefInfoRepo.ChildModelRefInfo" uuid="3067afb8-eabf-4702-a462-fb11be4b6e70">
      <modelName>sim_ROV_v0_R2018b</modelName>
      <modelPath>sim_ROV_v0_R2018b</modelPath>
    </childModelRefInfo>
    <dataTransferInfos>AAFJTQAAAAAOAAAAOAAAAAYAAAAIAAAAAgAAAAAAAAAFAAAACAAAAAAAAAABAAAAAQAAAAAAAAAFAAQAAQAAAAEAAAAAAAAA</dataTransferInfos>
    <defaultsCMapping>{&quot;Inports&quot;:&quot;{\&quot;Name\&quot;:\&quot;Default\&quot;,\&quot;Checksum\&quot;:\&quot;Default\&quot;,\&quot;PerInstancePropertiesChecksum\&quot;:\&quot;\&quot;,\&quot;MemorySectionName\&quot;:\&quot;None\&quot;,\&quot;MemorySectionChecksum\&quot;:\&quot;None\&quot;}&quot;,&quot;Outports&quot;:&quot;{\&quot;Name\&quot;:\&quot;Default\&quot;,\&quot;Checksum\&quot;:\&quot;Default\&quot;,\&quot;PerInstancePropertiesChecksum\&quot;:\&quot;\&quot;,\&quot;MemorySectionName\&quot;:\&quot;None\&quot;,\&quot;MemorySectionChecksum\&quot;:\&quot;None\&quot;}&quot;,&quot;ParameterArguments&quot;:&quot;{\&quot;Name\&quot;:\&quot;Default\&quot;,\&quot;Checksum\&quot;:\&quot;Default\&quot;,\&quot;PerInstancePropertiesChecksum\&quot;:\&quot;\&quot;,\&quot;MemorySectionName\&quot;:\&quot;None\&quot;,\&quot;MemorySectionChecksum\&quot;:\&quot;None\&quot;}&quot;,&quot;LocalParameters&quot;:&quot;{\&quot;Name\&quot;:\&quot;Default\&quot;,\&quot;Checksum\&quot;:\&quot;Default\&quot;,\&quot;PerInstancePropertiesChecksum\&quot;:\&quot;\&quot;,\&quot;MemorySectionName\&quot;:\&quot;None\&quot;,\&quot;MemorySectionChecksum\&quot;:\&quot;None\&quot;}&quot;,&quot;GlobalParameters&quot;:&quot;{\&quot;Name\&quot;:\&quot;Default\&quot;,\&quot;Checksum\&quot;:\&quot;Default\&quot;,\&quot;PerInstancePropertiesChecksum\&quot;:\&quot;\&quot;,\&quot;MemorySectionName\&quot;:\&quot;None\&quot;,\&quot;MemorySectionChecksum\&quot;:\&quot;None\&quot;}&quot;,&quot;InternalData&quot;:&quot;{\&quot;Name\&quot;:\&quot;Default\&quot;,\&quot;Checksum\&quot;:\&quot;Default\&quot;,\&quot;PerInstancePropertiesChecksum\&quot;:\&quot;\&quot;,\&quot;MemorySectionName\&quot;:\&quot;None\&quot;,\&quot;MemorySectionChecksum\&quot;:\&quot;None\&quot;}&quot;,&quot;SharedLocalDataStores&quot;:&quot;{\&quot;Name\&quot;:\&quot;Default\&quot;,\&quot;Checksum\&quot;:\&quot;Default\&quot;,\&quot;PerInstancePropertiesChecksum\&quot;:\&quot;\&quot;,\&quot;MemorySectionName\&quot;:\&quot;None\&quot;,\&quot;MemorySectionChecksum\&quot;:\&quot;None\&quot;}&quot;,&quot;GlobalDataStores&quot;:&quot;{\&quot;Name\&quot;:\&quot;Default\&quot;,\&quot;Checksum\&quot;:\&quot;Default\&quot;,\&quot;PerInstancePropertiesChecksum\&quot;:\&quot;\&quot;,\&quot;MemorySectionName\&quot;:\&quot;None\&quot;,\&quot;MemorySectionChecksum\&quot;:\&quot;None\&quot;}&quot;,&quot;Constants&quot;:&quot;{\&quot;Name\&quot;:\&quot;Default\&quot;,\&quot;Checksum\&quot;:\&quot;Default\&quot;,\&quot;PerInstancePropertiesChecksum\&quot;:\&quot;\&quot;,\&quot;MemorySectionName\&quot;:\&quot;None\&quot;,\&quot;MemorySectionChecksum\&quot;:\&quot;None\&quot;}&quot;,&quot;DataTransfers&quot;:&quot;{\&quot;Name\&quot;:\&quot;Default\&quot;,\&quot;Checksum\&quot;:\&quot;Default\&quot;,\&quot;PerInstancePropertiesChecksum\&quot;:\&quot;\&quot;,\&quot;MemorySectionName\&quot;:\&quot;None\&quot;,\&quot;MemorySectionChecksum\&quot;:\&quot;None\&quot;}&quot;,&quot;ModelData&quot;:&quot;{\&quot;Name\&quot;:\&quot;Default\&quot;,\&quot;Checksum\&quot;:\&quot;Default\&quot;,\&quot;PerInstancePropertiesChecksum\&quot;:\&quot;\&quot;,\&quot;MemorySectionName\&quot;:\&quot;None\&quot;,\&quot;MemorySectionChecksum\&quot;:\&quot;None\&quot;}&quot;,&quot;InitializeTerminate&quot;:&quot;{\&quot;Name\&quot;:\&quot;Default\&quot;,\&quot;Checksum\&quot;:\&quot;Default\&quot;,\&quot;PerInstancePropertiesChecksum\&quot;:\&quot;\&quot;,\&quot;MemorySectionName\&quot;:\&quot;None\&quot;,\&quot;MemorySectionChecksum\&quot;:\&quot;None\&quot;}&quot;,&quot;Execution&quot;:&quot;{\&quot;Name\&quot;:\&quot;Default\&quot;,\&quot;Checksum\&quot;:\&quot;Default\&quot;,\&quot;PerInstancePropertiesChecksum\&quot;:\&quot;\&quot;,\&quot;MemorySectionName\&quot;:\&quot;None\&quot;,\&quot;MemorySectionChecksum\&quot;:\&quot;None\&quot;}&quot;,&quot;SharedUtility&quot;:&quot;{\&quot;Name\&quot;:\&quot;Default\&quot;,\&quot;Checksum\&quot;:\&quot;Default\&quot;,\&quot;PerInstancePropertiesChecksum\&quot;:\&quot;\&quot;,\&quot;MemorySectionName\&quot;:\&quot;None\&quot;,\&quot;MemorySectionChecksum\&quot;:\&quot;None\&quot;}&quot;}</defaultsCMapping>
    <fastestNoncontSigFeedingDerivPorts>.01</fastestNoncontSigFeedingDerivPorts>
    <globalVariables>B</globalVariables>
    <globalVariables>D_linear</globalVariables>
    <globalVariables>D_quadratic</globalVariables>
    <globalVariables>I</globalVariables>
    <globalVariables>Kq</globalVariables>
    <globalVariables>Kx</globalVariables>
    <globalVariables>M_addedMass</globalVariables>
    <globalVariables>M_rigidBody</globalVariables>
    <globalVariables>TCM</globalVariables>
    <globalVariables>Ts</globalVariables>
    <globalVariables>W</globalVariables>
    <globalVariables>force</globalVariables>
    <globalVariables>m</globalVariables>
    <globalVariables>pwm</globalVariables>
    <globalVariables>r_b</globalVariables>
    <globalVariables>r_g</globalVariables>
    <globalVariables>sim_time</globalVariables>
    <hasBlockWithPeriodicDiscreteSampleTime>true</hasBlockWithPeriodicDiscreteSampleTime>
    <hasBwsAccessed>true</hasBwsAccessed>
    <hasBwsAccessedByAnyModel>true</hasBwsAccessedByAnyModel>
    <hasContinuousSampleTime>true</hasContinuousSampleTime>
    <hasNoncontSigFeedingDerivPorts>true</hasNoncontSigFeedingDerivPorts>
    <isBdInSimModeForSimCodegenVariants>false</isBdInSimModeForSimCodegenVariants>
    <loggingSaveFormat>2</loggingSaveFormat>
    <massMatrixNzMax>71</massMatrixNzMax>
    <maxFreqHz>-1.0</maxFreqHz>
    <needAbsoluteTimeDisallowInitPort>true</needAbsoluteTimeDisallowInitPort>
    <nonTunableVariables>M_addedMass</nonTunableVariables>
    <nonTunableVariables>M_rigidBody</nonTunableVariables>
    <nonTunableVariables>TCM</nonTunableVariables>
    <numCStateRecs>22</numCStateRecs>
    <numContinuousStates>71</numContinuousStates>
    <numDataInputPorts>0</numDataInputPorts>
    <numLoggableCStateRecs>22</numLoggableCStateRecs>
    <numLoggableJacobianDStates>0</numLoggableJacobianDStates>
    <runtimeNonFcnCallRateInfos type="ModelRefInfoRepo.RateInfo">
      <compiled>true</compiled>
      <needAbsoluteTime>true</needAbsoluteTime>
      <period>0.0</period>
      <priority>40</priority>
      <rateIdx>0</rateIdx>
    </runtimeNonFcnCallRateInfos>
    <runtimeNonFcnCallRateInfos type="ModelRefInfoRepo.RateInfo">
      <compiled>true</compiled>
      <nonFcnCallPartitionName>Cont</nonFcnCallPartitionName>
      <period>.01</period>
      <priority>40</priority>
      <rateIdx>1</rateIdx>
    </runtimeNonFcnCallRateInfos>
    <runtimeNonFcnCallRateInfos type="ModelRefInfoRepo.RateInfo">
      <compiled>true</compiled>
      <nonFcnCallPartitionName>Cont</nonFcnCallPartitionName>
      <period>.1</period>
      <priority>40</priority>
      <rateIdx>2</rateIdx>
    </runtimeNonFcnCallRateInfos>
    <sampleTimeInheritanceRule>2</sampleTimeInheritanceRule>
    <solverStatusFlags>323</solverStatusFlags>
    <timingAndTaskingRegistry>&lt;?xml version=&quot;1.0&quot;?&gt;
&lt;slexec_sto version=&quot;1.1&quot; packageUris=&quot;http://schema.mathworks.com/mf0/slexec_mm_sto/R2023a_202208151321&quot;&gt;
  &lt;sto.Registry type=&quot;sto.Registry&quot; uuid=&quot;141dd8c4-c866-4cff-8efd-13e3abc39e7e&quot;&gt;
    &lt;executionSpec&gt;Undetermined&lt;/executionSpec&gt;
    &lt;identifier&gt;sim_ROV_v0_R2018b&lt;/identifier&gt;
    &lt;clockRegistry type=&quot;sto.ClockRegistry&quot; uuid=&quot;668951fd-11ae-47e2-8d7d-cb9fc5778a44&quot;&gt;
      &lt;clocks type=&quot;sto.Timer&quot; uuid=&quot;b086fe4c-e9e5-4c44-ada6-e352f72896a4&quot;&gt;
        &lt;clockTickConstraint&gt;PeriodicWithFixedResolution&lt;/clockTickConstraint&gt;
        &lt;computedFundamentalDiscretePeriod&gt;.01&lt;/computedFundamentalDiscretePeriod&gt;
        &lt;fastestDiscreteRate type=&quot;sto.ClassicPeriodicDiscreteRate&quot; uuid=&quot;db1ade9c-aac1-4faa-a8b0-198b7f66b192&quot;/&gt;
        &lt;isDefaultTimer&gt;true&lt;/isDefaultTimer&gt;
        &lt;resolution&gt;.01&lt;/resolution&gt;
        &lt;timeAdvanceMode&gt;FixedStep&lt;/timeAdvanceMode&gt;
        &lt;identifier&gt;sim_ROV_v0_R2018b::defaultTimer&lt;/identifier&gt;
        &lt;rates type=&quot;sto.ContinuousRate&quot; uuid=&quot;3caa3878-b9ac-4be3-b72e-4c5765c9b038&quot;&gt;
          &lt;annotation&gt;Cont&lt;/annotation&gt;
          &lt;clockId&gt;sim_ROV_v0_R2018b::defaultTimer&lt;/clockId&gt;
          &lt;description&gt;Continuous&lt;/description&gt;
          &lt;taskId&gt;_task0&lt;/taskId&gt;
          &lt;rateSpec type=&quot;sto.RateSpec&quot; uuid=&quot;e718336f-f2ca-4b05-8313-a1a26e36558b&quot;/&gt;
        &lt;/rates&gt;
        &lt;rates type=&quot;sto.ClassicPeriodicDiscreteRate&quot; uuid=&quot;db1ade9c-aac1-4faa-a8b0-198b7f66b192&quot;&gt;
          &lt;annotation&gt;D1&lt;/annotation&gt;
          &lt;clockId&gt;sim_ROV_v0_R2018b::defaultTimer&lt;/clockId&gt;
          &lt;colorIndex&gt;2&lt;/colorIndex&gt;
          &lt;description&gt;Discrete 1&lt;/description&gt;
          &lt;rateIdx&gt;1&lt;/rateIdx&gt;
          &lt;taskId&gt;_task0&lt;/taskId&gt;
          &lt;rateSpec type=&quot;sto.RateSpec&quot; uuid=&quot;5db1aec5-7826-4b03-900e-d9865e8a1782&quot;&gt;
            &lt;period&gt;.01&lt;/period&gt;
            &lt;rateType&gt;ClassicPeriodicDiscrete&lt;/rateType&gt;
          &lt;/rateSpec&gt;
        &lt;/rates&gt;
        &lt;rates type=&quot;sto.ClassicPeriodicDiscreteRate&quot; uuid=&quot;f809c0e7-bb39-4764-9083-df23d1ca9049&quot;&gt;
          &lt;annotation&gt;D2&lt;/annotation&gt;
          &lt;clockId&gt;sim_ROV_v0_R2018b::defaultTimer&lt;/clockId&gt;
          &lt;colorIndex&gt;3&lt;/colorIndex&gt;
          &lt;description&gt;Discrete 2&lt;/description&gt;
          &lt;rateIdx&gt;2&lt;/rateIdx&gt;
          &lt;taskId&gt;_task0&lt;/taskId&gt;
          &lt;rateSpec type=&quot;sto.RateSpec&quot; uuid=&quot;03c642a6-e202-498d-8ca5-833f6b7ea668&quot;&gt;
            &lt;period&gt;.1&lt;/period&gt;
            &lt;rateType&gt;ClassicPeriodicDiscrete&lt;/rateType&gt;
          &lt;/rateSpec&gt;
        &lt;/rates&gt;
        &lt;baseRate type=&quot;sto.ContinuousRate&quot; uuid=&quot;8c4a758e-fc7b-4678-bcee-a08d65541c24&quot;&gt;
          &lt;annotation&gt;Cont&lt;/annotation&gt;
          &lt;clockId&gt;sim_ROV_v0_R2018b::defaultTimer&lt;/clockId&gt;
          &lt;description&gt;Continuous&lt;/description&gt;
          &lt;taskId&gt;_task0&lt;/taskId&gt;
          &lt;rateSpec type=&quot;sto.RateSpec&quot; uuid=&quot;d3e7a929-302d-4912-909f-cabd22fd7522&quot;/&gt;
        &lt;/baseRate&gt;
      &lt;/clocks&gt;
      &lt;clocks type=&quot;sto.Event&quot; uuid=&quot;400040bf-cfea-45ab-9da5-5c2f8587ad98&quot;&gt;
        &lt;eventType&gt;PARAMETER_CHANGE_EVENT&lt;/eventType&gt;
        &lt;cNum&gt;1&lt;/cNum&gt;
        &lt;clockType&gt;Event&lt;/clockType&gt;
        &lt;identifier&gt;ParameterChangeEvent&lt;/identifier&gt;
        &lt;rates type=&quot;sto.ModelWideEventRate&quot; uuid=&quot;def23d54-fe81-4e6d-89dc-0914cf7f955b&quot;&gt;
          &lt;clockId&gt;ParameterChangeEvent&lt;/clockId&gt;
          &lt;rateIdx&gt;-1&lt;/rateIdx&gt;
          &lt;taskId&gt;ModelWideParameterChangeEvent&lt;/taskId&gt;
          &lt;useForExecution&gt;NotForExecution&lt;/useForExecution&gt;
          &lt;rateSpec type=&quot;sto.RateSpec&quot; uuid=&quot;aff5f7a5-db69-4d9d-bfef-04ccd60d4654&quot;&gt;
            &lt;period&gt;inf&lt;/period&gt;
            &lt;rateType&gt;ModelWideParameterChangeEvent&lt;/rateType&gt;
          &lt;/rateSpec&gt;
        &lt;/rates&gt;
      &lt;/clocks&gt;
      &lt;timeAdvanceMode&gt;FixedStep&lt;/timeAdvanceMode&gt;
    &lt;/clockRegistry&gt;
    &lt;taskRegistry type=&quot;sto.TaskRegistry&quot; uuid=&quot;d1e6bc5e-b309-459b-a867-917673260f72&quot;&gt;
      &lt;rootTaskHierarchyElements type=&quot;sto.Task&quot; uuid=&quot;47d0f517-6012-48a7-b4d4-420b940c88a5&quot;&gt;
        &lt;isExplicit&gt;true&lt;/isExplicit&gt;
        &lt;rates type=&quot;sto.ModelWideEventRate&quot; uuid=&quot;5e49001b-e992-469b-9540-40b2b164d2d5&quot;&gt;
          &lt;clockId&gt;ParameterChangeEvent&lt;/clockId&gt;
          &lt;rateIdx&gt;-1&lt;/rateIdx&gt;
          &lt;taskId&gt;ModelWideParameterChangeEvent&lt;/taskId&gt;
          &lt;useForExecution&gt;NotForExecution&lt;/useForExecution&gt;
          &lt;rateSpec type=&quot;sto.RateSpec&quot; uuid=&quot;ff9da3d1-1625-4c7d-965b-33dd091b1289&quot;&gt;
            &lt;period&gt;inf&lt;/period&gt;
            &lt;rateType&gt;ModelWideParameterChangeEvent&lt;/rateType&gt;
          &lt;/rateSpec&gt;
        &lt;/rates&gt;
        &lt;schedulingClockId&gt;ParameterChangeEvent&lt;/schedulingClockId&gt;
        &lt;timeKeeperClockId&gt;sim_ROV_v0_R2018b::defaultTimer&lt;/timeKeeperClockId&gt;
        &lt;elementType&gt;Task&lt;/elementType&gt;
        &lt;identifier&gt;ModelWideParameterChangeEvent&lt;/identifier&gt;
        &lt;priority&gt;-1&lt;/priority&gt;
      &lt;/rootTaskHierarchyElements&gt;
      &lt;rootTaskHierarchyElements type=&quot;sto.Task&quot; uuid=&quot;d83efdef-6d33-4ebc-805e-a3f610eb7f34&quot;&gt;
        &lt;isExecutable&gt;true&lt;/isExecutable&gt;
        &lt;orderIndex&gt;1&lt;/orderIndex&gt;
        &lt;rates type=&quot;sto.ContinuousRate&quot; uuid=&quot;12f6f3a5-488b-49d5-b3f8-8fe141f10380&quot;&gt;
          &lt;annotation&gt;Cont&lt;/annotation&gt;
          &lt;clockId&gt;sim_ROV_v0_R2018b::defaultTimer&lt;/clockId&gt;
          &lt;description&gt;Continuous&lt;/description&gt;
          &lt;taskId&gt;_task0&lt;/taskId&gt;
          &lt;rateSpec type=&quot;sto.RateSpec&quot; uuid=&quot;a3b5aab2-dda7-4696-aafd-f0615bc76423&quot;/&gt;
        &lt;/rates&gt;
        &lt;rates type=&quot;sto.ClassicPeriodicDiscreteRate&quot; uuid=&quot;d44e8140-93f7-46d0-944f-2d9397f00982&quot;&gt;
          &lt;annotation&gt;D1&lt;/annotation&gt;
          &lt;clockId&gt;sim_ROV_v0_R2018b::defaultTimer&lt;/clockId&gt;
          &lt;colorIndex&gt;2&lt;/colorIndex&gt;
          &lt;description&gt;Discrete 1&lt;/description&gt;
          &lt;rateIdx&gt;1&lt;/rateIdx&gt;
          &lt;taskId&gt;_task0&lt;/taskId&gt;
          &lt;rateSpec type=&quot;sto.RateSpec&quot; uuid=&quot;589f58c3-edf9-475e-9362-c31f4a361cc5&quot;&gt;
            &lt;period&gt;.01&lt;/period&gt;
            &lt;rateType&gt;ClassicPeriodicDiscrete&lt;/rateType&gt;
          &lt;/rateSpec&gt;
        &lt;/rates&gt;
        &lt;rates type=&quot;sto.ClassicPeriodicDiscreteRate&quot; uuid=&quot;402f2c49-d0c2-4cbe-9995-3a8f4a39fec9&quot;&gt;
          &lt;annotation&gt;D2&lt;/annotation&gt;
          &lt;clockId&gt;sim_ROV_v0_R2018b::defaultTimer&lt;/clockId&gt;
          &lt;colorIndex&gt;3&lt;/colorIndex&gt;
          &lt;description&gt;Discrete 2&lt;/description&gt;
          &lt;rateIdx&gt;2&lt;/rateIdx&gt;
          &lt;taskId&gt;_task0&lt;/taskId&gt;
          &lt;rateSpec type=&quot;sto.RateSpec&quot; uuid=&quot;16340215-5856-4911-b19b-6994f77b383c&quot;&gt;
            &lt;period&gt;.1&lt;/period&gt;
            &lt;rateType&gt;ClassicPeriodicDiscrete&lt;/rateType&gt;
          &lt;/rateSpec&gt;
        &lt;/rates&gt;
        &lt;schedulingClockId&gt;sim_ROV_v0_R2018b::defaultTimer&lt;/schedulingClockId&gt;
        &lt;timeKeeperClockId&gt;sim_ROV_v0_R2018b::defaultTimer&lt;/timeKeeperClockId&gt;
        &lt;elementType&gt;Task&lt;/elementType&gt;
        &lt;identifier&gt;_task0&lt;/identifier&gt;
        &lt;priority&gt;40&lt;/priority&gt;
      &lt;/rootTaskHierarchyElements&gt;
      &lt;taskDependencyGraph type=&quot;sto.SerializedTaskConnectionList&quot; uuid=&quot;7802b672-6430-428b-a6dd-dc84bd0419ef&quot;&gt;
        &lt;clockIdentifier&gt;sim_ROV_v0_R2018b::defaultTimer&lt;/clockIdentifier&gt;
        &lt;taskIdentifier&gt;_task0&lt;/taskIdentifier&gt;
      &lt;/taskDependencyGraph&gt;
      &lt;taskDependencyGraph type=&quot;sto.SerializedTaskConnectionList&quot; uuid=&quot;b2a711c5-2510-449c-bf3c-816a1c024e99&quot;&gt;
        &lt;clockIdentifier&gt;ParameterChangeEvent&lt;/clockIdentifier&gt;
        &lt;taskIdentifier&gt;ModelWideParameterChangeEvent&lt;/taskIdentifier&gt;
      &lt;/taskDependencyGraph&gt;
      &lt;taskPriorityDirection&gt;HighNumberLast&lt;/taskPriorityDirection&gt;
    &lt;/taskRegistry&gt;
  &lt;/sto.Registry&gt;
&lt;/slexec_sto&gt;</timingAndTaskingRegistry>
    <FMUBlockMap type="ModelRefInfoRepo.FMUBlockInfo" uuid="05800512-f12f-4a3b-b2b1-1185b6107a05"/>
    <codeGenInfo type="ModelRefInfoRepo.CodeGenInformation" uuid="5323508f-5056-4afd-8097-773c9e5d7047"/>
    <compiledVariantInfos type="ModelRefInfoRepo.CompiledVariantInfoMap" uuid="8ae43405-5d9a-4ae6-af86-e4d3ce10ced8"/>
    <configSettingsForConsistencyChecks type="ModelRefInfoRepo.ConfigSettingsForConsistencyChecks" uuid="23d8f469-66a0-4d99-b923-5853f4718ff8">
      <consistentOutportInitialization>true</consistentOutportInitialization>
      <fixedStepSize>.01</fixedStepSize>
      <frameDiagnosticSetting>2</frameDiagnosticSetting>
      <hasHybridSampleTime>true</hasHybridSampleTime>
      <signalLoggingSaveFormat>2</signalLoggingSaveFormat>
      <simSIMDOptimization>1</simSIMDOptimization>
      <solverName>ode4</solverName>
      <solverType>SOLVER_TYPE_FIXEDSTEP</solverType>
      <hardwareSettings type="ModelRefInfoRepo.HardwareSettings" uuid="1d209ad2-22f3-4a86-84b2-1354aa47964a">
        <prodBitPerChar>8</prodBitPerChar>
        <prodBitPerDouble>64</prodBitPerDouble>
        <prodBitPerFloat>32</prodBitPerFloat>
        <prodBitPerInt>32</prodBitPerInt>
        <prodBitPerLong>32</prodBitPerLong>
        <prodBitPerLongLong>64</prodBitPerLongLong>
        <prodBitPerPointer>32</prodBitPerPointer>
        <prodBitPerPtrDiffT>32</prodBitPerPtrDiffT>
        <prodBitPerShort>16</prodBitPerShort>
        <prodBitPerSizeT>32</prodBitPerSizeT>
        <prodEndianess>1</prodEndianess>
        <prodLargestAtomicFloat>1</prodLargestAtomicFloat>
        <prodLargestAtomicInteger>3</prodLargestAtomicInteger>
        <prodShiftRight>true</prodShiftRight>
        <prodWordSize>32</prodWordSize>
      </hardwareSettings>
    </configSettingsForConsistencyChecks>
    <controllableInputRatesMap type="ModelRefInfoRepo.VarTsUIDMap" uuid="763e0ce9-df30-42f9-9966-b7ccc0340e51"/>
    <controllableOutputRatesMap type="ModelRefInfoRepo.VarTsUIDMap" uuid="eccb07d3-3425-4d58-829d-8bcede538601"/>
    <dataPortGroup type="ModelRefInfoRepo.DataPortGroup" uuid="755d8f0c-aa57-4f20-8f9f-bba3ebb9da34"/>
    <expFcnUnconnectedDataPortGroup type="ModelRefInfoRepo.DataPortGroup" uuid="74e9d96b-a286-4fde-96bb-ad1752e81058"/>
    <interfaceParameterInfo type="ModelRefInfoRepo.InterfaceParameterInfo" uuid="9f689dba-6aea-497b-aaf4-4b0e06d09eef">
      <globalVariables type="ModelRefInfoRepo.BuiltinParameter" uuid="2962ae97-8631-49aa-a593-f4d19bfea46e">
        <dimensions>1</dimensions>
        <dimensions>1</dimensions>
        <isUsed>true</isUsed>
        <numDimensions>2</numDimensions>
        <parameterName>B</parameterName>
      </globalVariables>
      <globalVariables type="ModelRefInfoRepo.BuiltinParameter" uuid="26f026a4-1022-4228-8095-c9d3c42dd4a9">
        <dimensions>6</dimensions>
        <dimensions>6</dimensions>
        <isUsed>true</isUsed>
        <numDimensions>2</numDimensions>
        <parameterName>D_linear</parameterName>
      </globalVariables>
      <globalVariables type="ModelRefInfoRepo.BuiltinParameter" uuid="95efbaad-6568-4178-b490-2f76d282c77e">
        <dimensions>6</dimensions>
        <dimensions>6</dimensions>
        <isUsed>true</isUsed>
        <numDimensions>2</numDimensions>
        <parameterName>D_quadratic</parameterName>
      </globalVariables>
      <globalVariables type="ModelRefInfoRepo.BuiltinParameter" uuid="5f0e01cb-95f3-40bc-91af-49edae428eb4">
        <dimensions>3</dimensions>
        <dimensions>3</dimensions>
        <isUsed>true</isUsed>
        <numDimensions>2</numDimensions>
        <parameterName>I</parameterName>
      </globalVariables>
      <globalVariables type="ModelRefInfoRepo.BuiltinParameter" uuid="3bfe62ec-3c9a-4065-9829-de88f4f947b4">
        <dimensions>6</dimensions>
        <dimensions>6</dimensions>
        <isUsed>true</isUsed>
        <numDimensions>2</numDimensions>
        <parameterName>Kq</parameterName>
      </globalVariables>
      <globalVariables type="ModelRefInfoRepo.BuiltinParameter" uuid="cbb4a10f-1a2b-449b-9e1f-c71824a2e499">
        <dimensions>6</dimensions>
        <dimensions>12</dimensions>
        <isUsed>true</isUsed>
        <numDimensions>2</numDimensions>
        <parameterName>Kx</parameterName>
      </globalVariables>
      <globalVariables type="ModelRefInfoRepo.BuiltinParameter" uuid="b32f92bd-df2c-477d-8867-d69a65ccc5ac">
        <dimensions>6</dimensions>
        <dimensions>6</dimensions>
        <isUsed>true</isUsed>
        <numDimensions>2</numDimensions>
        <parameterName>M_addedMass</parameterName>
      </globalVariables>
      <globalVariables type="ModelRefInfoRepo.BuiltinParameter" uuid="a124b30a-844f-44bd-ad81-596dcdb9f725">
        <dimensions>6</dimensions>
        <dimensions>8</dimensions>
        <isUsed>true</isUsed>
        <numDimensions>2</numDimensions>
        <parameterName>TCM</parameterName>
      </globalVariables>
      <globalVariables type="ModelRefInfoRepo.BuiltinParameter" uuid="f380fd71-679a-4185-afac-f673c0f2c507">
        <dimensions>1</dimensions>
        <dimensions>1</dimensions>
        <isUsed>true</isUsed>
        <numDimensions>2</numDimensions>
        <parameterName>W</parameterName>
      </globalVariables>
      <globalVariables type="ModelRefInfoRepo.BuiltinParameter" uuid="a83b3bcd-0f75-4643-9cd7-64bc7097c7c8">
        <dimensions>201</dimensions>
        <dimensions>1</dimensions>
        <isUsed>true</isUsed>
        <numDimensions>2</numDimensions>
        <parameterName>force</parameterName>
      </globalVariables>
      <globalVariables type="ModelRefInfoRepo.BuiltinParameter" uuid="baba0fdc-88d7-4a09-8f4f-ed9aa07c06b3">
        <dimensions>1</dimensions>
        <dimensions>1</dimensions>
        <isUsed>true</isUsed>
        <numDimensions>2</numDimensions>
        <parameterName>m</parameterName>
      </globalVariables>
      <globalVariables type="ModelRefInfoRepo.BuiltinParameter" uuid="3a067523-32d1-403e-8f64-b49e9078a9fd">
        <dimensions>201</dimensions>
        <dimensions>1</dimensions>
        <isUsed>true</isUsed>
        <numDimensions>2</numDimensions>
        <parameterName>pwm</parameterName>
      </globalVariables>
      <globalVariables type="ModelRefInfoRepo.BuiltinParameter" uuid="70853d75-574b-45f5-a70f-29d02c226d09">
        <dimensions>3</dimensions>
        <dimensions>1</dimensions>
        <isUsed>true</isUsed>
        <numDimensions>2</numDimensions>
        <parameterName>r_b</parameterName>
      </globalVariables>
      <globalVariables type="ModelRefInfoRepo.BuiltinParameter" uuid="341c8add-73e4-4153-9e4d-0e50d49b5f55">
        <dimensions>3</dimensions>
        <dimensions>1</dimensions>
        <isUsed>true</isUsed>
        <numDimensions>2</numDimensions>
        <parameterName>r_g</parameterName>
      </globalVariables>
    </interfaceParameterInfo>
    <messageInfo type="ModelRefInfoRepo.MessageInformation" uuid="1c77bbc6-b5fa-45e5-86f4-86a34219c045"/>
    <methodInfo type="ModelRefInfoRepo.MethodExistenceInfo" uuid="ab7df832-ade0-4b9b-8c0e-86a7c0dd2451">
      <hasDerivMethod>true</hasDerivMethod>
      <hasForcingFunctionMethod>true</hasForcingFunctionMethod>
      <hasSystemInitializeMethod>true</hasSystemInitializeMethod>
      <hasSystemResetMethod>true</hasSystemResetMethod>
      <hasTerminateMethod>true</hasTerminateMethod>
      <hasUpdateMethod>true</hasUpdateMethod>
    </methodInfo>
    <periodicEventPortUnsupportedBlockInfo type="ModelRefInfoRepo.PeriodicEventPortUnsupportedBlockInfo" uuid="47c675a6-a3d8-4d06-a6fb-49316f9f6e46">
      <deterministicRTBs>sim_ROV_v0_R2018b/Sensor Data and State Estimation/Internal Filter/Rate Transition</deterministicRTBs>
      <deterministicRTBs>sim_ROV_v0_R2018b/Sensor Data and State Estimation/Internal Filter/Rate Transition1</deterministicRTBs>
      <deterministicRTBs>sim_ROV_v0_R2018b/Sensor Data and State Estimation/Internal Filter/Rate Transition2</deterministicRTBs>
      <deterministicRTBs>sim_ROV_v0_R2018b/Sensor Data and State Estimation/Internal Filter/Rate Transition3</deterministicRTBs>
      <deterministicRTBs>sim_ROV_v0_R2018b/Sensor Data and State Estimation/Internal Filter/Rate Transition4</deterministicRTBs>
      <deterministicRTBs>sim_ROV_v0_R2018b/Sensor Data and State Estimation/Internal Filter/Rate Transition5</deterministicRTBs>
    </periodicEventPortUnsupportedBlockInfo>
    <portGroupsRequireSameRate type="ModelRefInfoRepo.PortGroupsRequireSameRate" uuid="f4931301-7b60-4fdd-a4bf-a446a10d038d">
      <DSMPortGroups type="ModelRefInfoRepo.NameToPortGroupIdxVectMap" uuid="e71db7eb-ae6c-4a91-a15a-dc91f95a57c6"/>
      <GlobalDSMPortGroups type="ModelRefInfoRepo.NameToPortGroupIdxVectMap" uuid="47d7d09f-1aee-4dcd-ac5a-8e25cb7f5a8b"/>
      <mergedPortGroups type="ModelRefInfoRepo.NameToPortGroupIdxVectMap" uuid="4b5dde0e-d03a-4b25-9e56-d0b03d559027"/>
    </portGroupsRequireSameRate>
    <rateBasedMdlGlobalDSMRateSpec type="ModelRefInfoRepo.GlobalDSMRateSpecMap" uuid="56e4b0f5-7e0b-483e-9feb-3cfcdd2b7db5"/>
    <rateSpecOfGlobalDSMAccessedByDescExpFcnMdlMap type="ModelRefInfoRepo.GlobalDSMRateSpecMap" uuid="25fe566f-9cd5-4d7a-adb4-b0fe801f091d"/>
    <rootBlockDiagramInterface type="ci.Model" uuid="0e0fd621-ad62-40e0-ad0c-2386f66a3365">
      <p_RootComponentInterface type="ci.ComponentInterface" uuid="506d644a-a771-435c-8b68-60ce4f1ebf5e">
        <p_Name>sim_ROV_v0_R2018b</p_Name>
        <p_Type>ROOT</p_Type>
      </p_RootComponentInterface>
    </rootBlockDiagramInterface>
    <simulinkFunctions type="ModelRefInfoRepo.SimulinkFunctions" uuid="4c1147ed-ab43-42b9-a150-c91e9e07ebf7">
      <compSimulinkFunctionCatalog></compSimulinkFunctionCatalog>
    </simulinkFunctions>
    <sltpContext type="sltp.mm.core.Context" uuid="6a3b3231-0435-460e-b31c-3a8279520a1e">
      <priorityDirection>HighNumberLast</priorityDirection>
      <defaultEventBehavior type="sltp.mm.core.EventBehavior" uuid="e324721f-5ff3-45e5-8c21-54d7490c8154"/>
      <editorState type="sltp.mm.core.EditorState" uuid="5eee4a73-dcc2-414f-a841-0389721d61f7">
        <isSynchronized>true</isSynchronized>
        <panelState type="sltp.mm.core.EditorPanelState" uuid="8ce5cc37-50a9-4f71-ac1e-ccfee49bcd81"/>
      </editorState>
      <rootTask type="sltp.mm.core.Task" uuid="58be4485-93a9-4777-a1a9-cf8eaf052b72">
        <context type="sltp.mm.core.Context" uuid="6a3b3231-0435-460e-b31c-3a8279520a1e"/>
        <explicit>false</explicit>
        <name>Default</name>
        <priority>-2147483648</priority>
        <subgraph type="sltp.mm.core.Graph" uuid="0e3e77a5-2bd1-4d05-b64f-84607b692483">
          <tasks type="sltp.mm.core.Task" uuid="5acfe5a8-1a08-4bef-a1eb-26602befdd1b">
            <baseTask>true</baseTask>
            <context type="sltp.mm.core.Context" uuid="6a3b3231-0435-460e-b31c-3a8279520a1e"/>
            <explicit>false</explicit>
            <id>1</id>
            <isTimed>true</isTimed>
            <name>Cont</name>
            <priority>40</priority>
            <rates type="sltp.mm.core.Rate" uuid="df93e8c5-7546-4918-bb95-dd0943ae195c">
              <annotation>Cont</annotation>
              <color>255</color>
              <hasBlocks>true</hasBlocks>
              <rateIndex>0</rateIndex>
              <rateSpec type="sltp.mm.core.RateSpec">
                <period>0.0</period>
              </rateSpec>
              <sti>0</sti>
            </rates>
            <rates type="sltp.mm.core.Rate" uuid="368ee42e-5f76-4fef-aeb4-f4f55adb16ac">
              <annotation>D1</annotation>
              <color>-436207361</color>
              <hasBlocks>true</hasBlocks>
              <rateIndex>1</rateIndex>
              <rateSpec type="sltp.mm.core.RateSpec">
                <period>.01</period>
              </rateSpec>
              <sti>1</sti>
            </rates>
            <rates type="sltp.mm.core.Rate" uuid="a92f4dfd-ae8d-43f4-bfec-18f09b556213">
              <annotation>D2</annotation>
              <color>13697279</color>
              <hasBlocks>true</hasBlocks>
              <rateIndex>2</rateIndex>
              <rateSpec type="sltp.mm.core.RateSpec">
                <period>.1</period>
              </rateSpec>
              <sti>2</sti>
            </rates>
          </tasks>
        </subgraph>
      </rootTask>
    </sltpContext>
    <stateWriterToOwnerMap type="ModelRefInfoRepo.StateWriterInfo" uuid="d9a3cc3a-8717-4c02-9d60-8a749e8b6b2a"/>
    <stoClientDataRegistry type="sto.ClientDataRegistry" uuid="ce006ec9-22d4-410a-bc04-524703bbf714">
      <dataSets type="sto.ClientClockNamedDataSet" uuid="2657125e-6cb9-4bf1-9ca1-4276377d9465">
        <tag>sltpEvents</tag>
      </dataSets>
      <dataSets type="sto.ClientTaskHierarchyElementNamedDataSet" uuid="990150bc-a251-4bba-b6d7-b789e4eae3ef">
        <tag>sltpTaskGroups</tag>
      </dataSets>
      <dataSets type="sto.ClientTaskHierarchyElementNamedDataSet" uuid="0e835c08-c06f-409c-b561-9bbf33e4f7cb">
        <dSet type="ModelRefInfoRepo.SltpTaskData" uuid="9752f2ce-493d-4aa1-830b-42dce0393157"/>
        <tSet type="ModelRefInfoRepo.SltpTaskData" uuid="9752f2ce-493d-4aa1-830b-42dce0393157">
          <dataName>Cont</dataName>
          <linkedSet type="sto.ClientTaskHierarchyElementNamedDataSet" uuid="0e835c08-c06f-409c-b561-9bbf33e4f7cb"/>
          <id type="sto.TaskHierarchyElementId">
            <clockId>sim_ROV_v0_R2018b::defaultTimer</clockId>
            <id>_task0</id>
          </id>
        </tSet>
        <tag>sltpTasks</tag>
      </dataSets>
    </stoClientDataRegistry>
    <varTsUIDMap type="ModelRefInfoRepo.VarTsUIDMap" uuid="539b72c4-449c-4494-9205-a27038e19e64"/>
  </ModelRefInfoRepo.ModelRefInfoRoot>
</MF0>